uaua/__init__.py
uaua/__main__.py
uaua/uauator.py
uaua-0.1.dist-info/METADATA
uaua-0.1.dist-info/WHEEL
uaua-0.1.dist-info/top_level.txt
uaua-0.1.dist-info/RECORD
