Metadata-Version: 2.4
Name: uaua
Version: 0.1
Summary: A command line program to test the writing speed of your terminal
Author-email: NumbersTada <tadaktatak61@gmail.com>
Classifier: Programming Language :: Python :: 3
Classifier: Operating System :: OS Independent
Classifier: License :: OSI Approved :: MIT License
Requires-Python: >=3.6
